PySide/__init__.py
PySide/_utils.py
PySide/libpyside.cpython-33m.1.2.2.dylib
PySide/libpyside.cpython-33m.1.2.dylib
PySide/libpyside.cpython-33m.dylib
PySide/libshiboken.cpython-33m.1.2.2.dylib
PySide/libshiboken.cpython-33m.1.2.dylib
PySide/libshiboken.cpython-33m.dylib
PySide/phonon.so
PySide/pyside-lupdate
PySide/pyside-rcc
PySide/QtCore.so
PySide/QtDeclarative.so
PySide/QtGui.so
PySide/QtHelp.so
PySide/QtMultimedia.so
PySide/QtNetwork.so
PySide/QtOpenGL.so
PySide/QtScript.so
PySide/QtScriptTools.so
PySide/QtSql.so
PySide/QtSvg.so
PySide/QtTest.so
PySide/QtUiTools.so
PySide/QtWebKit.so
PySide/QtXml.so
PySide/QtXmlPatterns.so
PySide/shiboken
PySide/shiboken.so
PySide/examples/README
PySide/examples/animation/animatedtiles/animatedtiles.py
PySide/examples/animation/animatedtiles/animatedtiles.qrc
PySide/examples/animation/animatedtiles/animatedtiles_rc.py
PySide/examples/animation/animatedtiles/images/centered.png
PySide/examples/animation/animatedtiles/images/ellipse.png
PySide/examples/animation/animatedtiles/images/figure8.png
PySide/examples/animation/animatedtiles/images/kinetic.png
PySide/examples/animation/animatedtiles/images/random.png
PySide/examples/animation/animatedtiles/images/tile.png
PySide/examples/animation/animatedtiles/images/Time-For-Lunch-2.jpg
PySide/examples/animation/appchooser/accessories-dictionary.png
PySide/examples/animation/appchooser/akregator.png
PySide/examples/animation/appchooser/appchooser.py
PySide/examples/animation/appchooser/appchooser.qrc
PySide/examples/animation/appchooser/appchooser_rc.py
PySide/examples/animation/appchooser/digikam.png
PySide/examples/animation/appchooser/k3b.png
PySide/examples/animation/easing/easing.py
PySide/examples/animation/easing/easing.qrc
PySide/examples/animation/easing/easing_rc.py
PySide/examples/animation/easing/form.ui
PySide/examples/animation/easing/ui_form.py
PySide/examples/animation/easing/images/qt-logo.png
PySide-1.2.2.dist-info/DESCRIPTION.rst
PySide-1.2.2.dist-info/entry_points.txt
PySide-1.2.2.dist-info/METADATA
PySide-1.2.2.dist-info/metadata.json
PySide-1.2.2.dist-info/RECORD
PySide-1.2.2.dist-info/top_level.txt
PySide-1.2.2.dist-info/WHEEL
